mdi_pil/__init__.py
mdi_pil/_variables.scss
mdi_pil/constants.py
mdi_pil/materialdesignicons-webfont.ttf
mdi_pil/ttkbootstrap_mdi.py
mdi_pil-1.1.7.dist-info/LICENSE
mdi_pil-1.1.7.dist-info/METADATA
mdi_pil-1.1.7.dist-info/WHEEL
mdi_pil-1.1.7.dist-info/top_level.txt
mdi_pil-1.1.7.dist-info/RECORD
