Metadata-Version: 2.2
Name: mdi_pil
Version: 1.1.7
Summary: A library to draw MDI icons onto PIL Image objects.
Author: Slalamander
License:                     GNU GENERAL PUBLIC LICENSE
Project-URL: Homepage, https://github.com/Slalamander/mdi_pil
Project-URL: source, https://github.com/Slalamander/mdi_pil
Keywords: mdi,MaterialDesignIcon,pictogrammers,mdi icons,ttkbootstrap,tkinter,tk
Classifier: Programming Language :: Python :: 3
Classifier: Operating System :: OS Independent
Classifier: License :: OSI Approved :: GNU General Public License v3 (GPLv3)
Requires-Python: >=3.9
License-File: LICENSE
Requires-Dist: Pillow
Provides-Extra: ttk
Requires-Dist: ttkbootstrap; extra == "ttk"
